ionoscloud/__init__.py
ionoscloud/api_client.py
ionoscloud/configuration.py
ionoscloud/exceptions.py
ionoscloud/rest.py
ionoscloud/api/__api.py
ionoscloud/api/__init__.py
ionoscloud/api/application_load_balancers_api.py
ionoscloud/api/backup_units_api.py
ionoscloud/api/contract_resources_api.py
ionoscloud/api/data_centers_api.py
ionoscloud/api/firewall_rules_api.py
ionoscloud/api/flow_logs_api.py
ionoscloud/api/images_api.py
ionoscloud/api/ip_blocks_api.py
ionoscloud/api/kubernetes_api.py
ionoscloud/api/labels_api.py
ionoscloud/api/lans_api.py
ionoscloud/api/load_balancers_api.py
ionoscloud/api/locations_api.py
ionoscloud/api/nat_gateways_api.py
ionoscloud/api/network_interfaces_api.py
ionoscloud/api/network_load_balancers_api.py
ionoscloud/api/private_cross_connects_api.py
ionoscloud/api/requests_api.py
ionoscloud/api/security_groups_api.py
ionoscloud/api/servers_api.py
ionoscloud/api/snapshots_api.py
ionoscloud/api/target_groups_api.py
ionoscloud/api/templates_api.py
ionoscloud/api/user_management_api.py
ionoscloud/api/user_s3_keys_api.py
ionoscloud/api/volumes_api.py
ionoscloud/models/__init__.py
ionoscloud/models/application_load_balancer.py
ionoscloud/models/application_load_balancer_entities.py
ionoscloud/models/application_load_balancer_forwarding_rule.py
ionoscloud/models/application_load_balancer_forwarding_rule_properties.py
ionoscloud/models/application_load_balancer_forwarding_rule_put.py
ionoscloud/models/application_load_balancer_forwarding_rules.py
ionoscloud/models/application_load_balancer_http_rule.py
ionoscloud/models/application_load_balancer_http_rule_condition.py
ionoscloud/models/application_load_balancer_properties.py
ionoscloud/models/application_load_balancer_put.py
ionoscloud/models/application_load_balancers.py
ionoscloud/models/attached_volumes.py
ionoscloud/models/backup_unit.py
ionoscloud/models/backup_unit_properties.py
ionoscloud/models/backup_unit_sso.py
ionoscloud/models/backup_units.py
ionoscloud/models/balanced_nics.py
ionoscloud-6.1.13.dist-info/LICENSE
ionoscloud-6.1.13.dist-info/METADATA
ionoscloud-6.1.13.dist-info/WHEEL
ionoscloud-6.1.13.dist-info/top_level.txt
ionoscloud-6.1.13.dist-info/RECORD
